gpu_stats/__init__.py
gpu_stats/cli.py
gpu_stats/components.py
gpu_stats/demo.py
gpu_stats/monitor.py
gpu_stats_cli-0.1.0.dist-info/licenses/LICENSE
gpu_stats_cli-0.1.0.dist-info/METADATA
gpu_stats_cli-0.1.0.dist-info/WHEEL
gpu_stats_cli-0.1.0.dist-info/entry_points.txt
gpu_stats_cli-0.1.0.dist-info/top_level.txt
gpu_stats_cli-0.1.0.dist-info/RECORD
